cs/tagset.py
cs_tagset-20250528.dist-info/WHEEL
cs_tagset-20250528.dist-info/METADATA
cs_tagset-20250528.dist-info/RECORD
