Metadata-Version: 2.4
Name: cs-tagset
Version: 20250528
Summary: Tags and sets of tags with __format__ support and optional ontology information.
Keywords: python3
Author-email: Cameron Simpson <cs@cskk.id.au>
Classifier: Programming Language :: Python
Classifier: Programming Language :: Python :: 3
Classifier: Development Status :: 4 - Beta
Classifier: Intended Audience :: Developers
Classifier: Operating System :: OS Independent
Classifier: Topic :: Software Development :: Libraries :: Python Modules
Classifier: License :: OSI Approved :: GNU General Public License v3 or later (GPLv3+)
Requires-Dist: cs.cmdutils>=20210404
Requires-Dist: cs.context>=20250528
Requires-Dist: cs.dateutils>=20230210
Requires-Dist: cs.deco>=20250513
Requires-Dist: cs.edit>=20220429
Requires-Dist: cs.fileutils>=20250528
Requires-Dist: cs.fs>=20220429
Requires-Dist: cs.lex>=20250428
Requires-Dist: cs.logutils>=20250323
Requires-Dist: cs.mappings>=20250528
Requires-Dist: cs.obj>=20200716
Requires-Dist: cs.pfx>=20250308
Requires-Dist: cs.py3>=20220523
Requires-Dist: cs.resources>=20250325
Requires-Dist: cs.threads>=20250528
Requires-Dist: icontract
Requires-Dist: typeguard
Project-URL: MonoRepo Commits, https://bitbucket.org/cameron_simpson/css/commits/branch/main
Project-URL: Monorepo Git Mirror, https://github.com/cameron-simpson/css
Project-URL: Monorepo Hg/Mercurial Mirror, https://hg.sr.ht/~cameron-simpson/css
Project-URL: Source, https://github.com/cameron-simpson/css/blob/main/lib/python/cs/tagset.py
